ps_utils/__init__.py
ps_utils/conversors.py
ps_utils/exceptions.py
ps_utils/montage.py
ps_utils/objects.py
ps_utils/settings.py
ps_utils-1.0.1.dist-info/METADATA
ps_utils-1.0.1.dist-info/WHEEL
ps_utils-1.0.1.dist-info/top_level.txt
ps_utils-1.0.1.dist-info/RECORD
