Metadata-Version: 2.1
Name: ps-utils
Version: 1.0.1
Summary: Personalized stationery utilities
Home-page: https://github.com/richard-alexsander/image-montage-maker
Author: ri_guima
Author-email: richardalexsander611@gmail.com
License: UNKNOWN
Platform: UNKNOWN
Classifier: Programming Language :: Python :: 3
Classifier: License :: OSI Approved :: MIT License
Classifier: Operating System :: OS Independent
Requires-Python: >=3.6
Requires-Dist: opencv-python
